AUTHORS.rst
CONTRIBUTING.rst
HISTORY.rst
LICENSE
MANIFEST.in
README.rst
setup.cfg
setup.py
docs/Makefile
docs/authors.rst
docs/conf.py
docs/contributing.rst
docs/history.rst
docs/index.rst
docs/installation.rst
docs/make.bat
docs/readme.rst
docs/usage.rst
hostsmgr/__init__.py
hostsmgr/conditions.py
hostsmgr/entries.py
hostsmgr/exceptions.py
hostsmgr/hostsmgr.py
hostsmgr.egg-info/PKG-INFO
hostsmgr.egg-info/SOURCES.txt
hostsmgr.egg-info/dependency_links.txt
hostsmgr.egg-info/not-zip-safe
hostsmgr.egg-info/requires.txt
hostsmgr.egg-info/top_level.txt
tests/__init__.py
tests/test_hostsmgr.py
tests/data/hosts.txt